amr_logic_converter/AmrContext.py
amr_logic_converter/AmrLogicConverter.py
amr_logic_converter/__init__.py
amr_logic_converter/extract_instances_from_amr_tree.py
amr_logic_converter/find_coreferent_instances.py
amr_logic_converter/find_instance_depths.py
amr_logic_converter/map_instances_lca.py
amr_logic_converter/map_instances_to_nodes.py
amr_logic_converter/parse_symbol_and_alignment.py
amr_logic_converter/py.typed
amr_logic_converter/types.py
amr_logic_converter-0.11.3.dist-info/LICENSE
amr_logic_converter-0.11.3.dist-info/METADATA
amr_logic_converter-0.11.3.dist-info/WHEEL
amr_logic_converter-0.11.3.dist-info/RECORD
