Metadata-Version: 2.1
Name: amr-logic-converter
Version: 0.11.3
Summary: Convert Abstract Meaning Representation (AMR) into first-order logic
Home-page: https://github.com/chanind/amr-logic-converter
License: MIT
Keywords: amr,logic,first-order-logic,nlp,abstract-meaning-representation
Author: David Chanin
Author-email: chanindav@gmail.com
Requires-Python: >=3.10,<4.0
Classifier: License :: OSI Approved :: MIT License
Classifier: Programming Language :: Python :: 3
Classifier: Programming Language :: Python :: 3.10
Classifier: Programming Language :: Python :: 3.11
Classifier: Programming Language :: Python :: 3.12
Requires-Dist: Penman (>=1.2.2,<2.0.0)
Requires-Dist: typing-extensions (>=3.7.4)
Project-URL: Repository, https://github.com/chanind/amr-logic-converter
